sky_ceiling_projector-1.0.0.dist-info/licenses/LICENSE
sky_projector/__init__.py
sky_projector/main.py
sky_projector/projector.py
sky_ceiling_projector-1.0.0.dist-info/METADATA
sky_ceiling_projector-1.0.0.dist-info/WHEEL
sky_ceiling_projector-1.0.0.dist-info/entry_points.txt
sky_ceiling_projector-1.0.0.dist-info/top_level.txt
sky_ceiling_projector-1.0.0.dist-info/RECORD
