Metadata-Version: 2.4
Name: sky-ceiling-projector
Version: 1.0.0
Summary: A realistic sky ceiling projector with weather effects, celestial objects, and enhanced starfield
Home-page: https://github.com/yourusername/sky-ceiling-projector
Author: Sky Projector Team
Author-email: Sky Projector Team <your-email@example.com>
Maintainer-email: Sky Projector Team <your-email@example.com>
License: MIT
Project-URL: Homepage, https://github.com/yourusername/sky-ceiling-projector
Project-URL: Documentation, https://github.com/yourusername/sky-ceiling-projector#readme
Project-URL: Repository, https://github.com/yourusername/sky-ceiling-projector.git
Project-URL: Bug Reports, https://github.com/yourusername/sky-ceiling-projector/issues
Project-URL: Changelog, https://github.com/yourusername/sky-ceiling-projector/blob/main/CHANGELOG.md
Keywords: astronomy,projector,ceiling,sky,weather,stars,moon,planets,pygame,raspberry-pi
Classifier: Development Status :: 5 - Production/Stable
Classifier: Intended Audience :: End Users/Desktop
Classifier: Topic :: Multimedia :: Graphics :: Presentation
Classifier: Topic :: Scientific/Engineering :: Astronomy
Classifier: License :: OSI Approved :: MIT License
Classifier: Programming Language :: Python :: 3
Classifier: Programming Language :: Python :: 3.8
Classifier: Programming Language :: Python :: 3.9
Classifier: Programming Language :: Python :: 3.10
Classifier: Programming Language :: Python :: 3.11
Classifier: Programming Language :: Python :: 3.12
Classifier: Operating System :: OS Independent
Classifier: Environment :: X11 Applications
Requires-Python: >=3.8
License-File: LICENSE
Requires-Dist: pygame>=2.0.0
Requires-Dist: requests>=2.25.0
Requires-Dist: numpy>=1.20.0
Requires-Dist: pytz>=2021.1
Provides-Extra: enhanced
Requires-Dist: geopy>=2.0.0; extra == "enhanced"
Requires-Dist: timezonefinder>=6.0.0; extra == "enhanced"
Provides-Extra: dev
Requires-Dist: pytest>=6.0; extra == "dev"
Requires-Dist: black>=21.0; extra == "dev"
Requires-Dist: flake8>=3.8; extra == "dev"
Requires-Dist: build>=0.7.0; extra == "dev"
Requires-Dist: twine>=3.4.0; extra == "dev"
Dynamic: author
Dynamic: home-page
Dynamic: license-file
Dynamic: requires-python
